{"_ts":[1577841391,1577885213,1577929058,1577972599],"_r":{"breakdown":{"html":{"bytes":[24774,24643,24692,24692],"requests":[9,9,9,10]},"js":{"bytes":[916599,917472,916611,915905],"requests":[30,31,30,29]},"css":{"bytes":[180946,180946,180946,180946],"requests":[3,3,3,3]},"image":{"bytes":[1315268,1315226,1315268,1315232],"requests":[46,46,46,45]},"flash":{"bytes":[0,0,0,0],"requests":[0,0,0,0]},"font":{"bytes":[126180,126180,126180,126180],"requests":[5,5,5,5]},"video":{"bytes":[0,0,0,0],"requests":[0,0,0,0]},"other":{"bytes":[301,301,301,301],"requests":[3,3,3,3]}},"date":[1577841391,1577885213,1577929058,1577972599],"domElements":[2737,2746,2737,2735],"domInteractive":[1564,1676,1559,1515],"firstPaint":[1288.8699999967,1351.2400000036,1284.1049999988,1317.7549999964],"fullyLoaded":[8535,9103,8811,9160],"id":["200101_84_f2c0f7aabdd28491e335fd5ad18ced0a","200101_AC_494a580f7e8a4d19b1b6624bef17f278","200102_8V_ecf6ab78931633799fe889e814a0e183","200102_1H_4e019ef96a2c99aff3aaa32ef67c0418"],"loadTime":[5916,5594,5417,5500],"render":[1200,1300,1300,1300],"SpeedIndex":[3514,3311,3272,3235],"TTFB":[483,503,466,496],"videoFrames":[[{"_i":"ms_000000.jpg","_t":0,"_vc":0},{"_i":"ms_001200.jpg","_t":1200,"_vc":0},{"_i":"ms_001400.jpg","_t":1400,"_vc":34},{"_i":"ms_001500.jpg","_t":1500,"_vc":35},{"_i":"ms_001700.jpg","_t":1700,"_vc":47},{"_i":"ms_001800.jpg","_t":1800,"_vc":51},{"_i":"ms_002000.jpg","_t":2000,"_vc":52},{"_i":"ms_002100.jpg","_t":2100,"_vc":51},{"_i":"ms_002200.jpg","_t":2200,"_vc":51},{"_i":"ms_002900.jpg","_t":2900,"_vc":51},{"_i":"ms_003400.jpg","_t":3400,"_vc":51},{"_i":"ms_003500.jpg","_t":3500,"_vc":40},{"_i":"ms_004000.jpg","_t":4000,"_vc":41},{"_i":"ms_004100.jpg","_t":4100,"_vc":41},{"_i":"ms_004200.jpg","_t":4200,"_vc":41},{"_i":"ms_004500.jpg","_t":4500,"_vc":61},{"_i":"ms_005500.jpg","_t":5500,"_vc":88},{"_i":"ms_005900.jpg","_t":5900,"_vc":100}],[{"_i":"ms_000000.jpg","_t":0,"_vc":0},{"_i":"ms_001300.jpg","_t":1300,"_vc":0},{"_i":"ms_001500.jpg","_t":1500,"_vc":34},{"_i":"ms_001700.jpg","_t":1700,"_vc":35},{"_i":"ms_001800.jpg","_t":1800,"_vc":47},{"_i":"ms_001900.jpg","_t":1900,"_vc":51},{"_i":"ms_002000.jpg","_t":2000,"_vc":52},{"_i":"ms_002100.jpg","_t":2100,"_vc":52},{"_i":"ms_002200.jpg","_t":2200,"_vc":51},{"_i":"ms_002900.jpg","_t":2900,"_vc":41},{"_i":"ms_003900.jpg","_t":3900,"_vc":65},{"_i":"ms_004900.jpg","_t":4900,"_vc":81},{"_i":"ms_005600.jpg","_t":5600,"_vc":100}],[{"_i":"ms_000000.jpg","_t":0,"_vc":0},{"_i":"ms_001300.jpg","_t":1300,"_vc":0},{"_i":"ms_001500.jpg","_t":1500,"_vc":34},{"_i":"ms_001600.jpg","_t":1600,"_vc":35},{"_i":"ms_001800.jpg","_t":1800,"_vc":47},{"_i":"ms_001900.jpg","_t":1900,"_vc":51},{"_i":"ms_002100.jpg","_t":2100,"_vc":52},{"_i":"ms_002200.jpg","_t":2200,"_vc":51},{"_i":"ms_002300.jpg","_t":2300,"_vc":51},{"_i":"ms_002400.jpg","_t":2400,"_vc":51},{"_i":"ms_002800.jpg","_t":2800,"_vc":41},{"_i":"ms_003800.jpg","_t":3800,"_vc":64},{"_i":"ms_004800.jpg","_t":4800,"_vc":81},{"_i":"ms_005500.jpg","_t":5500,"_vc":100}],[{"_i":"ms_000000.jpg","_t":0,"_vc":0},{"_i":"ms_001300.jpg","_t":1300,"_vc":1},{"_i":"ms_001500.jpg","_t":1500,"_vc":34},{"_i":"ms_001600.jpg","_t":1600,"_vc":35},{"_i":"ms_001800.jpg","_t":1800,"_vc":47},{"_i":"ms_002000.jpg","_t":2000,"_vc":48},{"_i":"ms_002100.jpg","_t":2100,"_vc":47},{"_i":"ms_002200.jpg","_t":2200,"_vc":47},{"_i":"ms_002300.jpg","_t":2300,"_vc":51},{"_i":"ms_002700.jpg","_t":2700,"_vc":51},{"_i":"ms_002800.jpg","_t":2800,"_vc":44},{"_i":"ms_004000.jpg","_t":4000,"_vc":70},{"_i":"ms_005000.jpg","_t":5000,"_vc":85},{"_i":"ms_005400.jpg","_t":5400,"_vc":100}]],"visualComplete":[5900,5600,5500,5400],"lighthouse":[31,31,31,31],"pagespeed":[52,51,52,48]}}